dtcoords/VERSION
dtcoords/__about__.py
dtcoords/__init__.py
dtcoords/datetimecoord.py
datetimecoords-0.1.0.dist-info/METADATA
datetimecoords-0.1.0.dist-info/WHEEL
datetimecoords-0.1.0.dist-info/licenses/LICENSE
datetimecoords-0.1.0.dist-info/RECORD
