Metadata-Version: 2.4
Name: datetimecoords
Version: 0.1.0
Summary: A package to provide tools to handle computations with datetime-like data.
Project-URL: repository, https://github.com/C0nrado/dtcoords
Author-email: Conrado <souza.conrado@gmail.com>
License-Expression: MIT
License-File: LICENSE
Classifier: Development Status :: 4 - Beta
Classifier: Operating System :: OS Independent
Classifier: Programming Language :: Python :: 3 :: Only
Classifier: Programming Language :: Python :: 3.9
Classifier: Topic :: Software Development :: Libraries
Requires-Dist: numpy>=1.20
Requires-Dist: pandas>=1.1.5
